easy_utility/__init__.py
easy_utility/gcp/__init__.py
easy_utility/gcp/google_vision/__init__.py
easy_utility/gcp/google_vision/detect_text_in_files.py
easy_utility-0.1.2.dist-info/METADATA
easy_utility-0.1.2.dist-info/WHEEL
easy_utility-0.1.2.dist-info/top_level.txt
easy_utility-0.1.2.dist-info/RECORD
